pysharedoscom/__init__.py
pysharedoscom/menu.py
pysharedoscom/table.py
pysharedoscom-2.0.dist-info/LICENCE.txt
pysharedoscom-2.0.dist-info/METADATA
pysharedoscom-2.0.dist-info/WHEEL
pysharedoscom-2.0.dist-info/top_level.txt
pysharedoscom-2.0.dist-info/RECORD
