Metadata-Version: 2.1
Name: pysharedoscom
Version: 2.0
Summary: Pyshare Library
Home-page: UNKNOWN
Author: Aldhiya Rozak
Author-email: Aldhiya.rozak@gmail.com
License: MIT
Keywords: menu
Platform: UNKNOWN
Classifier: Development Status :: 5 - Production/Stable
Classifier: Intended Audience :: Education
Classifier: Operating System :: Microsoft :: Windows :: Windows 10
Classifier: License :: OSI Approved :: MIT License
Classifier: Programming Language :: Python :: 3
License-File: LICENCE.txt
